README.md
setup.cfg
setup.py
yonwog/CurrencyRouletteGame.py
yonwog/Game.py
yonwog/GuessGame.py
yonwog/Helper_funcs.py
yonwog/Live.py
yonwog/MainGame.py
yonwog/MemoryGame.py
yonwog/__init__.py
yonwog/wog.py
yonwog.egg-info/PKG-INFO
yonwog.egg-info/SOURCES.txt
yonwog.egg-info/dependency_links.txt
yonwog.egg-info/requires.txt
yonwog.egg-info/top_level.txt